{
  "heroesPos1": {
    "winDay": [
      {
        "heroId": 1,
        "matchCount": 1498,
        "winCount": 693
      },
      {
        "heroId": 2,
        "matchCount": 10,
        "winCount": 4
      },
      {
        "heroId": 3,
        "matchCount": 2,
        "winCount": 1
      },
      {
        "heroId": 4,
        "matchCount": 221,
        "winCount": 127
      },
      {
        "heroId": 5,
        "matchCount": 3,
        "winCount": 2
      },
      {
        "heroId": 6,
        "matchCount": 1647,
        "winCount": 842
      },
      {
        "heroId": 7,
        "matchCount": 6,
        "winCount": 4
      },
      {
        "heroId": 8,
        "matchCount": 1514,
        "winCount": 772
      },
      {
        "heroId": 9,
        "matchCount": 34,
        "winCount": 12
      },
      {
        "heroId": 10,
        "matchCount": 1424,
        "winCount": 704
      },
      {
        "heroId": 11,
        "matchCount": 2177,
        "winCount": 1086
      },
      {
        "heroId": 12,
        "matchCount": 1046,
        "winCount": 537
      },
      {
        "heroId": 13,
        "matchCount": 4,
        "winCount": 3
      },
      {
        "heroId": 14,
        "matchCount": 140,
        "winCount": 75
      },
      {
        "heroId": 15,
        "matchCount": 556,
        "winCount": 275
      },
      {
        "heroId": 16,
        "matchCount": 7,
        "winCount": 6
      },
      {
        "heroId": 17,
        "matchCount": 105,
        "winCount": 45
      },
      {
        "heroId": 18,
        "matchCount": 495,
        "winCount": 226
      },
      {
        "heroId": 19,
        "matchCount": 61,
        "winCount": 37
      },
      {
        "heroId": 20,
        "matchCount": 27,
        "winCount": 22
      },
      {
        "heroId": 21,
        "matchCount": 873,
        "winCount": 447
      },
      {
        "heroId": 22,
        "matchCount": 6,
        "winCount": 3
      },
      {
        "heroId": 23,
        "matchCount": 10,
        "winCount": 4
      },
      {
        "heroId": 25,
        "matchCount": 104,
        "winCount": 45
      },
      {
        "heroId": 26,
        "matchCount": 10,
        "winCount": 4
      },
      {
        "heroId": 27,
        "matchCount": 4,
        "winCount": 1
      },
      {
        "heroId": 28,
        "matchCount": 15,
        "winCount": 10
      },
      {
        "heroId": 29,
        "matchCount": 8,
        "winCount": 4
      },
      {
        "heroId": 30,
        "matchCount": 4,
        "winCount": 3
      },
      {
        "heroId": 31,
        "matchCount": 8,
        "winCount": 1
      },
      {
        "heroId": 32,
        "matchCount": 204,
        "winCount": 114
      },
      {
        "heroId": 33,
        "matchCount": 2,
        "winCount": 1
      },
      {
        "heroId": 34,
        "matchCount": 25,
        "winCount": 15
      },
      {
        "heroId": 35,
        "matchCount": 139,
        "winCount": 72
      },
      {
        "heroId": 36,
        "matchCount": 108,
        "winCount": 59
      },
      {
        "heroId": 37,
        "matchCount": 3,
        "winCount": 2
      },
      {
        "heroId": 38,
        "matchCount": 91,
        "winCount": 45
      },
      {
        "heroId": 39,
        "matchCount": 51,
        "winCount": 19
      },
      {
        "heroId": 40,
        "matchCount": 15,
        "winCount": 7
      },
      {
        "heroId": 41,
        "matchCount": 964,
        "winCount": 480
      },
      {
        "heroId": 42,
        "matchCount": 263,
        "winCount": 140
      },
      {
        "heroId": 43,
        "matchCount": 7,
        "winCount": 3
      },
      {
        "heroId": 44,
        "matchCount": 1098,
        "winCount": 546
      },
      {
        "heroId": 46,
        "matchCount": 1003,
        "winCount": 503
      },
      {
        "heroId": 47,
        "matchCount": 176,
        "winCount": 89
      },
      {
        "heroId": 48,
        "matchCount": 1120,
        "winCount": 554
      },
      {
        "heroId": 49,
        "matchCount": 411,
        "winCount": 193
      },
      {
        "heroId": 50,
        "matchCount": 7,
        "winCount": 5
      },
      {
        "heroId": 51,
        "matchCount": 2,
        "winCount": 1
      },
      {
        "heroId": 52,
        "matchCount": 37,
        "winCount": 19
      },
      {
        "heroId": 53,
        "matchCount": 193,
        "winCount": 99
      },
      {
        "heroId": 54,
        "matchCount": 763,
        "winCount": 386
      },
      {
        "heroId": 55,
        "matchCount": 1,
        "winCount": 0
      },
      {
        "heroId": 56,
        "matchCount": 1681,
        "winCount": 905
      },
      {
        "heroId": 57,
        "matchCount": 65,
        "winCount": 30
      },
      {
        "heroId": 58,
        "matchCount": 9,
        "winCount": 4
      },
      {
        "heroId": 59,
        "matchCount": 125,
        "winCount": 66
      },
      {
        "heroId": 60,
        "matchCount": 19,
        "winCount": 10
      },
      {
        "heroId": 61,
        "matchCount": 181,
        "winCount": 101
      },
      {
        "heroId": 62,
        "matchCount": 8,
        "winCount": 3
      },
      {
        "heroId": 63,
        "matchCount": 914,
        "winCount": 461
      },
      {
        "heroId": 64,
        "matchCount": 7,
        "winCount": 4
      },
      {
        "heroId": 65,
        "matchCount": 17,
        "winCount": 8
      },
      {
        "heroId": 67,
        "matchCount": 614,
        "winCount": 318
      },
      {
        "heroId": 69,
        "matchCount": 9,
        "winCount": 4
      },
      {
        "heroId": 70,
        "matchCount": 1413,
        "winCount": 703
      },
      {
        "heroId": 71,
        "matchCount": 5,
        "winCount": 1
      },
      {
        "heroId": 72,
        "matchCount": 857,
        "winCount": 393
      },
      {
        "heroId": 73,
        "matchCount": 174,
        "winCount": 76
      },
      {
        "heroId": 74,
        "matchCount": 6,
        "winCount": 3
      },
      {
        "heroId": 75,
        "matchCount": 8,
        "winCount": 2
      },
      {
        "heroId": 76,
        "matchCount": 18,
        "winCount": 16
      },
      {
        "heroId": 77,
        "matchCount": 18,
        "winCount": 6
      },
      {
        "heroId": 78,
        "matchCount": 8,
        "winCount": 4
      },
      {
        "heroId": 79,
        "matchCount": 1,
        "winCount": 1
      },
      {
        "heroId": 80,
        "matchCount": 45,
        "winCount": 19
      },
      {
        "heroId": 81,
        "matchCount": 254,
        "winCount": 139
      },
      {
        "heroId": 82,
        "matchCount": 66,
        "winCount": 39
      },
      {
        "heroId": 83,
        "matchCount": 7,
        "winCount": 3
      },
      {
        "heroId": 84,
        "matchCount": 10,
        "winCount": 7
      },
      {
        "heroId": 85,
        "matchCount": 6,
        "winCount": 2
      },
      {
        "heroId": 86,
        "matchCount": 7,
        "winCount": 4
      },
      {
        "heroId": 87,
        "matchCount": 4,
        "winCount": 1
      },
      {
        "heroId": 88,
        "matchCount": 6,
        "winCount": 3
      },
      {
        "heroId": 89,
        "matchCount": 137,
        "winCount": 73
      },
      {
        "heroId": 90,
        "matchCount": 2,
        "winCount": 2
      },
      {
        "heroId": 91,
        "matchCount": 14,
        "winCount": 9
      },
      {
        "heroId": 92,
        "matchCount": 14,
        "winCount": 6
      },
      {
        "heroId": 93,
        "matchCount": 2200,
        "winCount": 1125
      },
      {
        "heroId": 94,
        "matchCount": 529,
        "winCount": 264
      },
      {
        "heroId": 95,
        "matchCount": 231,
        "winCount": 110
      },
      {
        "heroId": 97,
        "matchCount": 27,
        "winCount": 12
      },
      {
        "heroId": 98,
        "matchCount": 11,
        "winCount": 5
      },
      {
        "heroId": 99,
        "matchCount": 41,
        "winCount": 24
      },
      {
        "heroId": 100,
        "matchCount": 4,
        "winCount": 0
      },
      {
        "heroId": 101,
        "matchCount": 1,
        "winCount": 0
      },
      {
        "heroId": 102,
        "matchCount": 139,
        "winCount": 70
      },
      {
        "heroId": 103,
        "matchCount": 3,
        "winCount": 1
      },
      {
        "heroId": 104,
        "matchCount": 24,
        "winCount": 15
      },
      {
        "heroId": 105,
        "matchCount": 14,
        "winCount": 6
      },
      {
        "heroId": 106,
        "matchCount": 19,
        "winCount": 9
      },
      {
        "heroId": 107,
        "matchCount": 2,
        "winCount": 0
      },
      {
        "heroId": 108,
        "matchCount": 27,
        "winCount": 12
      },
      {
        "heroId": 109,
        "matchCount": 422,
        "winCount": 193
      },
      {
        "heroId": 110,
        "matchCount": 1,
        "winCount": 0
      },
      {
        "heroId": 111,
        "matchCount": 2,
        "winCount": 0
      },
      {
        "heroId": 112,
        "matchCount": 5,
        "winCount": 2
      },
      {
        "heroId": 113,
        "matchCount": 31,
        "winCount": 18
      },
      {
        "heroId": 114,
        "matchCount": 351,
        "winCount": 158
      },
      {
        "heroId": 119,
        "matchCount": 8,
        "winCount": 4
      },
      {
        "heroId": 120,
        "matchCount": 6,
        "winCount": 1
      },
      {
        "heroId": 121,
        "matchCount": 3,
        "winCount": 0
      },
      {
        "heroId": 123,
        "matchCount": 10,
        "winCount": 6
      },
      {
        "heroId": 126,
        "matchCount": 20,
        "winCount": 13
      },
      {
        "heroId": 128,
        "matchCount": 2,
        "winCount": 0
      },
      {
        "heroId": 129,
        "matchCount": 12,
        "winCount": 4
      },
      {
        "heroId": 135,
        "matchCount": 10,
        "winCount": 4
      },
      {
        "heroId": 136,
        "matchCount": 86,
        "winCount": 53
      },
      {
        "heroId": 137,
        "matchCount": 3,
        "winCount": 2
      },
      {
        "heroId": 138,
        "matchCount": 722,
        "winCount": 357
      },
      {
        "heroId": 145,
        "matchCount": 510,
        "winCount": 215
      },
      {
        "heroId": 155,
        "matchCount": 16,
        "winCount": 9
      }
    ],
    "winWeek": null
  },
  "heroesPos2": {
    "winDay": [
      {
        "heroId": 1,
        "matchCount": 82,
        "winCount": 35
      },
      {
        "heroId": 2,
        "matchCount": 46,
        "winCount": 24
      },
      {
        "heroId": 3,
        "matchCount": 27,
        "winCount": 11
      },
      {
        "heroId": 4,
        "matchCount": 37,
        "winCount": 15
      },
      {
        "heroId": 5,
        "matchCount": 22,
        "winCount": 11
      },
      {
        "heroId": 6,
        "matchCount": 22,
        "winCount": 11
      },
      {
        "heroId": 7,
        "matchCount": 306,
        "winCount": 149
      },
      {
        "heroId": 8,
        "matchCount": 5,
        "winCount": 1
      },
      {
        "heroId": 9,
        "matchCount": 96,
        "winCount": 47
      },
      {
        "heroId": 10,
        "matchCount": 79,
        "winCount": 32
      },
      {
        "heroId": 11,
        "matchCount": 1251,
        "winCount": 604
      },
      {
        "heroId": 12,
        "matchCount": 5,
        "winCount": 1
      },
      {
        "heroId": 13,
        "matchCount": 1297,
        "winCount": 659
      },
      {
        "heroId": 14,
        "matchCount": 434,
        "winCount": 225
      },
      {
        "heroId": 15,
        "matchCount": 333,
        "winCount": 162
      },
      {
        "heroId": 16,
        "matchCount": 132,
        "winCount": 69
      },
      {
        "heroId": 17,
        "matchCount": 1480,
        "winCount": 730
      },
      {
        "heroId": 18,
        "matchCount": 5,
        "winCount": 2
      },
      {
        "heroId": 19,
        "matchCount": 708,
        "winCount": 339
      },
      {
        "heroId": 20,
        "matchCount": 34,
        "winCount": 11
      },
      {
        "heroId": 21,
        "matchCount": 391,
        "winCount": 188
      },
      {
        "heroId": 22,
        "matchCount": 527,
        "winCount": 235
      },
      {
        "heroId": 23,
        "matchCount": 238,
        "winCount": 116
      },
      {
        "heroId": 25,
        "matchCount": 1053,
        "winCount": 518
      },
      {
        "heroId": 26,
        "matchCount": 181,
        "winCount": 76
      },
      {
        "heroId": 27,
        "matchCount": 10,
        "winCount": 4
      },
      {
        "heroId": 28,
        "matchCount": 234,
        "winCount": 118
      },
      {
        "heroId": 29,
        "matchCount": 22,
        "winCount": 13
      },
      {
        "heroId": 30,
        "matchCount": 15,
        "winCount": 8
      },
      {
        "heroId": 31,
        "matchCount": 13,
        "winCount": 6
      },
      {
        "heroId": 32,
        "matchCount": 166,
        "winCount": 89
      },
      {
        "heroId": 33,
        "matchCount": 38,
        "winCount": 22
      },
      {
        "heroId": 34,
        "matchCount": 833,
        "winCount": 425
      },
      {
        "heroId": 35,
        "matchCount": 916,
        "winCount": 417
      },
      {
        "heroId": 36,
        "matchCount": 921,
        "winCount": 434
      },
      {
        "heroId": 37,
        "matchCount": 10,
        "winCount": 4
      },
      {
        "heroId": 38,
        "matchCount": 322,
        "winCount": 165
      },
      {
        "heroId": 39,
        "matchCount": 2072,
        "winCount": 1042
      },
      {
        "heroId": 40,
        "matchCount": 46,
        "winCount": 21
      },
      {
        "heroId": 41,
        "matchCount": 34,
        "winCount": 15
      },
      {
        "heroId": 42,
        "matchCount": 5,
        "winCount": 3
      },
      {
        "heroId": 43,
        "matchCount": 218,
        "winCount": 92
      },
      {
        "heroId": 44,
        "matchCount": 11,
        "winCount": 4
      },
      {
        "heroId": 45,
        "matchCount": 57,
        "winCount": 23
      },
      {
        "heroId": 46,
        "matchCount": 108,
        "winCount": 50
      },
      {
        "heroId": 47,
        "matchCount": 703,
        "winCount": 326
      },
      {
        "heroId": 48,
        "matchCount": 19,
        "winCount": 12
      },
      {
        "heroId": 49,
        "matchCount": 291,
        "winCount": 143
      },
      {
        "heroId": 50,
        "matchCount": 40,
        "winCount": 18
      },
      {
        "heroId": 51,
        "matchCount": 5,
        "winCount": 3
      },
      {
        "heroId": 52,
        "matchCount": 802,
        "winCount": 419
      },
      {
        "heroId": 53,
        "matchCount": 229,
        "winCount": 108
      },
      {
        "heroId": 54,
        "matchCount": 3,
        "winCount": 3
      },
      {
        "heroId": 55,
        "matchCount": 7,
        "winCount": 1
      },
      {
        "heroId": 56,
        "matchCount": 218,
        "winCount": 115
      },
      {
        "heroId": 57,
        "matchCount": 44,
        "winCount": 20
      },
      {
        "heroId": 58,
        "matchCount": 17,
        "winCount": 11
      },
      {
        "heroId": 59,
        "matchCount": 924,
        "winCount": 470
      },
      {
        "heroId": 60,
        "matchCount": 39,
        "winCount": 16
      },
      {
        "heroId": 61,
        "matchCount": 298,
        "winCount": 174
      },
      {
        "heroId": 62,
        "matchCount": 41,
        "winCount": 18
      },
      {
        "heroId": 63,
        "matchCount": 36,
        "winCount": 16
      },
      {
        "heroId": 64,
        "matchCount": 46,
        "winCount": 22
      },
      {
        "heroId": 65,
        "matchCount": 159,
        "winCount": 96
      },
      {
        "heroId": 66,
        "matchCount": 1,
        "winCount": 0
      },
      {
        "heroId": 67,
        "matchCount": 9,
        "winCount": 5
      },
      {
        "heroId": 68,
        "matchCount": 32,
        "winCount": 10
      },
      {
        "heroId": 69,
        "matchCount": 41,
        "winCount": 16
      },
      {
        "heroId": 70,
        "matchCount": 26,
        "winCount": 13
      },
      {
        "heroId": 71,
        "matchCount": 42,
        "winCount": 20
      },
      {
        "heroId": 72,
        "matchCount": 17,
        "winCount": 7
      },
      {
        "heroId": 73,
        "matchCount": 122,
        "winCount": 61
      },
      {
        "heroId": 74,
        "matchCount": 2488,
        "winCount": 1308
      },
      {
        "heroId": 75,
        "matchCount": 40,
        "winCount": 14
      },
      {
        "heroId": 76,
        "matchCount": 705,
        "winCount": 375
      },
      {
        "heroId": 77,
        "matchCount": 54,
        "winCount": 26
      },
      {
        "heroId": 78,
        "matchCount": 25,
        "winCount": 15
      },
      {
        "heroId": 79,
        "matchCount": 10,
        "winCount": 1
      },
      {
        "heroId": 80,
        "matchCount": 166,
        "winCount": 94
      },
      {
        "heroId": 81,
        "matchCount": 44,
        "winCount": 25
      },
      {
        "heroId": 82,
        "matchCount": 221,
        "winCount": 134
      },
      {
        "heroId": 83,
        "matchCount": 4,
        "winCount": 3
      },
      {
        "heroId": 84,
        "matchCount": 60,
        "winCount": 33
      },
      {
        "heroId": 85,
        "matchCount": 27,
        "winCount": 13
      },
      {
        "heroId": 86,
        "matchCount": 801,
        "winCount": 393
      },
      {
        "heroId": 87,
        "matchCount": 4,
        "winCount": 2
      },
      {
        "heroId": 88,
        "matchCount": 171,
        "winCount": 85
      },
      {
        "heroId": 89,
        "matchCount": 4,
        "winCount": 2
      },
      {
        "heroId": 90,
        "matchCount": 273,
        "winCount": 150
      },
      {
        "heroId": 91,
        "matchCount": 39,
        "winCount": 22
      },
      {
        "heroId": 92,
        "matchCount": 151,
        "winCount": 80
      },
      {
        "heroId": 93,
        "matchCount": 115,
        "winCount": 61
      },
      {
        "heroId": 94,
        "matchCount": 23,
        "winCount": 9
      },
      {
        "heroId": 95,
        "matchCount": 5,
        "winCount": 3
      },
      {
        "heroId": 96,
        "matchCount": 26,
        "winCount": 9
      },
      {
        "heroId": 97,
        "matchCount": 356,
        "winCount": 181
      },
      {
        "heroId": 98,
        "matchCount": 171,
        "winCount": 90
      },
      {
        "heroId": 99,
        "matchCount": 45,
        "winCount": 17
      },
      {
        "heroId": 100,
        "matchCount": 99,
        "winCount": 51
      },
      {
        "heroId": 101,
        "matchCount": 492,
        "winCount": 235
      },
      {
        "heroId": 102,
        "matchCount": 28,
        "winCount": 16
      },
      {
        "heroId": 103,
        "matchCount": 5,
        "winCount": 3
      },
      {
        "heroId": 104,
        "matchCount": 70,
        "winCount": 37
      },
      {
        "heroId": 105,
        "matchCount": 32,
        "winCount": 12
      },
      {
        "heroId": 106,
        "matchCount": 1646,
        "winCount": 808
      },
      {
        "heroId": 107,
        "matchCount": 268,
        "winCount": 145
      },
      {
        "heroId": 108,
        "matchCount": 37,
        "winCount": 14
      },
      {
        "heroId": 109,
        "matchCount": 6,
        "winCount": 4
      },
      {
        "heroId": 110,
        "matchCount": 201,
        "winCount": 100
      },
      {
        "heroId": 111,
        "matchCount": 31,
        "winCount": 15
      },
      {
        "heroId": 112,
        "matchCount": 31,
        "winCount": 20
      },
      {
        "heroId": 113,
        "matchCount": 407,
        "winCount": 222
      },
      {
        "heroId": 114,
        "matchCount": 273,
        "winCount": 135
      },
      {
        "heroId": 119,
        "matchCount": 49,
        "winCount": 24
      },
      {
        "heroId": 120,
        "matchCount": 144,
        "winCount": 75
      },
      {
        "heroId": 121,
        "matchCount": 15,
        "winCount": 7
      },
      {
        "heroId": 123,
        "matchCount": 21,
        "winCount": 6
      },
      {
        "heroId": 126,
        "matchCount": 777,
        "winCount": 381
      },
      {
        "heroId": 128,
        "matchCount": 47,
        "winCount": 16
      },
      {
        "heroId": 129,
        "matchCount": 88,
        "winCount": 46
      },
      {
        "heroId": 131,
        "matchCount": 4,
        "winCount": 2
      },
      {
        "heroId": 135,
        "matchCount": 83,
        "winCount": 40
      },
      {
        "heroId": 136,
        "matchCount": 236,
        "winCount": 156
      },
      {
        "heroId": 137,
        "matchCount": 278,
        "winCount": 150
      },
      {
        "heroId": 138,
        "matchCount": 108,
        "winCount": 44
      },
      {
        "heroId": 145,
        "matchCount": 243,
        "winCount": 130
      },
      {
        "heroId": 155,
        "matchCount": 114,
        "winCount": 67
      }
    ],
    "winWeek": null
  },
  "heroesPos3": {
    "winDay": [
      {
        "heroId": 1,
        "matchCount": 25,
        "winCount": 11
      },
      {
        "heroId": 2,
        "matchCount": 1930,
        "winCount": 926
      },
      {
        "heroId": 3,
        "matchCount": 2,
        "winCount": 1
      },
      {
        "heroId": 4,
        "matchCount": 31,
        "winCount": 12
      },
      {
        "heroId": 5,
        "matchCount": 14,
        "winCount": 7
      },
      {
        "heroId": 6,
        "matchCount": 7,
        "winCount": 2
      },
      {
        "heroId": 7,
        "matchCount": 390,
        "winCount": 174
      },
      {
        "heroId": 8,
        "matchCount": 13,
        "winCount": 6
      },
      {
        "heroId": 9,
        "matchCount": 41,
        "winCount": 15
      },
      {
        "heroId": 10,
        "matchCount": 10,
        "winCount": 2
      },
      {
        "heroId": 11,
        "matchCount": 19,
        "winCount": 10
      },
      {
        "heroId": 12,
        "matchCount": 12,
        "winCount": 10
      },
      {
        "heroId": 13,
        "matchCount": 10,
        "winCount": 5
      },
      {
        "heroId": 14,
        "matchCount": 893,
        "winCount": 488
      },
      {
        "heroId": 15,
        "matchCount": 2301,
        "winCount": 1231
      },
      {
        "heroId": 16,
        "matchCount": 316,
        "winCount": 169
      },
      {
        "heroId": 17,
        "matchCount": 20,
        "winCount": 9
      },
      {
        "heroId": 18,
        "matchCount": 17,
        "winCount": 6
      },
      {
        "heroId": 19,
        "matchCount": 392,
        "winCount": 164
      },
      {
        "heroId": 20,
        "matchCount": 140,
        "winCount": 78
      },
      {
        "heroId": 21,
        "matchCount": 399,
        "winCount": 192
      },
      {
        "heroId": 22,
        "matchCount": 23,
        "winCount": 10
      },
      {
        "heroId": 23,
        "matchCount": 343,
        "winCount": 180
      },
      {
        "heroId": 25,
        "matchCount": 12,
        "winCount": 5
      },
      {
        "heroId": 26,
        "matchCount": 21,
        "winCount": 6
      },
      {
        "heroId": 27,
        "matchCount": 6,
        "winCount": 1
      },
      {
        "heroId": 28,
        "matchCount": 1093,
        "winCount": 559
      },
      {
        "heroId": 29,
        "matchCount": 1390,
        "winCount": 684
      },
      {
        "heroId": 30,
        "matchCount": 7,
        "winCount": 3
      },
      {
        "heroId": 31,
        "matchCount": 7,
        "winCount": 2
      },
      {
        "heroId": 32,
        "matchCount": 73,
        "winCount": 39
      },
      {
        "heroId": 33,
        "matchCount": 309,
        "winCount": 164
      },
      {
        "heroId": 34,
        "matchCount": 28,
        "winCount": 12
      },
      {
        "heroId": 35,
        "matchCount": 29,
        "winCount": 12
      },
      {
        "heroId": 36,
        "matchCount": 472,
        "winCount": 230
      },
      {
        "heroId": 37,
        "matchCount": 8,
        "winCount": 2
      },
      {
        "heroId": 38,
        "matchCount": 705,
        "winCount": 324
      },
      {
        "heroId": 39,
        "matchCount": 194,
        "winCount": 95
      },
      {
        "heroId": 40,
        "matchCount": 131,
        "winCount": 70
      },
      {
        "heroId": 41,
        "matchCount": 129,
        "winCount": 68
      },
      {
        "heroId": 42,
        "matchCount": 297,
        "winCount": 154
      },
      {
        "heroId": 43,
        "matchCount": 236,
        "winCount": 124
      },
      {
        "heroId": 44,
        "matchCount": 13,
        "winCount": 5
      },
      {
        "heroId": 45,
        "matchCount": 13,
        "winCount": 5
      },
      {
        "heroId": 46,
        "matchCount": 5,
        "winCount": 3
      },
      {
        "heroId": 47,
        "matchCount": 515,
        "winCount": 261
      },
      {
        "heroId": 48,
        "matchCount": 7,
        "winCount": 4
      },
      {
        "heroId": 49,
        "matchCount": 205,
        "winCount": 110
      },
      {
        "heroId": 50,
        "matchCount": 41,
        "winCount": 24
      },
      {
        "heroId": 51,
        "matchCount": 43,
        "winCount": 18
      },
      {
        "heroId": 52,
        "matchCount": 57,
        "winCount": 28
      },
      {
        "heroId": 53,
        "matchCount": 92,
        "winCount": 35
      },
      {
        "heroId": 54,
        "matchCount": 15,
        "winCount": 9
      },
      {
        "heroId": 55,
        "matchCount": 408,
        "winCount": 184
      },
      {
        "heroId": 56,
        "matchCount": 19,
        "winCount": 5
      },
      {
        "heroId": 57,
        "matchCount": 769,
        "winCount": 423
      },
      {
        "heroId": 58,
        "matchCount": 32,
        "winCount": 18
      },
      {
        "heroId": 59,
        "matchCount": 165,
        "winCount": 85
      },
      {
        "heroId": 60,
        "matchCount": 681,
        "winCount": 345
      },
      {
        "heroId": 61,
        "matchCount": 101,
        "winCount": 48
      },
      {
        "heroId": 62,
        "matchCount": 48,
        "winCount": 22
      },
      {
        "heroId": 63,
        "matchCount": 120,
        "winCount": 49
      },
      {
        "heroId": 64,
        "matchCount": 27,
        "winCount": 12
      },
      {
        "heroId": 65,
        "matchCount": 218,
        "winCount": 106
      },
      {
        "heroId": 66,
        "matchCount": 1,
        "winCount": 0
      },
      {
        "heroId": 67,
        "matchCount": 8,
        "winCount": 4
      },
      {
        "heroId": 68,
        "matchCount": 4,
        "winCount": 3
      },
      {
        "heroId": 69,
        "matchCount": 274,
        "winCount": 145
      },
      {
        "heroId": 70,
        "matchCount": 53,
        "winCount": 28
      },
      {
        "heroId": 71,
        "matchCount": 170,
        "winCount": 90
      },
      {
        "heroId": 72,
        "matchCount": 18,
        "winCount": 8
      },
      {
        "heroId": 73,
        "matchCount": 92,
        "winCount": 42
      },
      {
        "heroId": 74,
        "matchCount": 37,
        "winCount": 18
      },
      {
        "heroId": 75,
        "matchCount": 11,
        "winCount": 5
      },
      {
        "heroId": 76,
        "matchCount": 14,
        "winCount": 10
      },
      {
        "heroId": 77,
        "matchCount": 146,
        "winCount": 64
      },
      {
        "heroId": 78,
        "matchCount": 445,
        "winCount": 222
      },
      {
        "heroId": 79,
        "matchCount": 2,
        "winCount": 0
      },
      {
        "heroId": 80,
        "matchCount": 74,
        "winCount": 41
      },
      {
        "heroId": 81,
        "matchCount": 255,
        "winCount": 127
      },
      {
        "heroId": 82,
        "matchCount": 6,
        "winCount": 3
      },
      {
        "heroId": 83,
        "matchCount": 45,
        "winCount": 27
      },
      {
        "heroId": 84,
        "matchCount": 171,
        "winCount": 76
      },
      {
        "heroId": 85,
        "matchCount": 340,
        "winCount": 161
      },
      {
        "heroId": 86,
        "matchCount": 61,
        "winCount": 27
      },
      {
        "heroId": 87,
        "matchCount": 1,
        "winCount": 0
      },
      {
        "heroId": 88,
        "matchCount": 106,
        "winCount": 60
      },
      {
        "heroId": 89,
        "matchCount": 11,
        "winCount": 5
      },
      {
        "heroId": 90,
        "matchCount": 17,
        "winCount": 6
      },
      {
        "heroId": 91,
        "matchCount": 27,
        "winCount": 12
      },
      {
        "heroId": 92,
        "matchCount": 209,
        "winCount": 107
      },
      {
        "heroId": 93,
        "matchCount": 105,
        "winCount": 52
      },
      {
        "heroId": 94,
        "matchCount": 11,
        "winCount": 7
      },
      {
        "heroId": 95,
        "matchCount": 10,
        "winCount": 5
      },
      {
        "heroId": 96,
        "matchCount": 1034,
        "winCount": 513
      },
      {
        "heroId": 97,
        "matchCount": 1003,
        "winCount": 477
      },
      {
        "heroId": 98,
        "matchCount": 929,
        "winCount": 444
      },
      {
        "heroId": 99,
        "matchCount": 399,
        "winCount": 160
      },
      {
        "heroId": 100,
        "matchCount": 105,
        "winCount": 57
      },
      {
        "heroId": 101,
        "matchCount": 19,
        "winCount": 7
      },
      {
        "heroId": 102,
        "matchCount": 128,
        "winCount": 61
      },
      {
        "heroId": 103,
        "matchCount": 49,
        "winCount": 22
      },
      {
        "heroId": 104,
        "matchCount": 1727,
        "winCount": 898
      },
      {
        "heroId": 105,
        "matchCount": 16,
        "winCount": 8
      },
      {
        "heroId": 106,
        "matchCount": 51,
        "winCount": 23
      },
      {
        "heroId": 107,
        "matchCount": 107,
        "winCount": 67
      },
      {
        "heroId": 108,
        "matchCount": 1627,
        "winCount": 839
      },
      {
        "heroId": 109,
        "matchCount": 21,
        "winCount": 10
      },
      {
        "heroId": 110,
        "matchCount": 328,
        "winCount": 169
      },
      {
        "heroId": 111,
        "matchCount": 2,
        "winCount": 0
      },
      {
        "heroId": 112,
        "matchCount": 97,
        "winCount": 54
      },
      {
        "heroId": 113,
        "matchCount": 5,
        "winCount": 3
      },
      {
        "heroId": 114,
        "matchCount": 59,
        "winCount": 23
      },
      {
        "heroId": 119,
        "matchCount": 16,
        "winCount": 11
      },
      {
        "heroId": 120,
        "matchCount": 112,
        "winCount": 46
      },
      {
        "heroId": 121,
        "matchCount": 5,
        "winCount": 2
      },
      {
        "heroId": 123,
        "matchCount": 19,
        "winCount": 7
      },
      {
        "heroId": 126,
        "matchCount": 140,
        "winCount": 72
      },
      {
        "heroId": 128,
        "matchCount": 58,
        "winCount": 25
      },
      {
        "heroId": 129,
        "matchCount": 1968,
        "winCount": 941
      },
      {
        "heroId": 131,
        "matchCount": 1,
        "winCount": 0
      },
      {
        "heroId": 135,
        "matchCount": 637,
        "winCount": 316
      },
      {
        "heroId": 136,
        "matchCount": 124,
        "winCount": 81
      },
      {
        "heroId": 137,
        "matchCount": 589,
        "winCount": 287
      },
      {
        "heroId": 138,
        "matchCount": 28,
        "winCount": 12
      },
      {
        "heroId": 145,
        "matchCount": 40,
        "winCount": 19
      },
      {
        "heroId": 155,
        "matchCount": 664,
        "winCount": 395
      }
    ],
    "winWeek": null
  },
  "heroesPos4": {
    "winDay": [
      {
        "heroId": 1,
        "matchCount": 4,
        "winCount": 2
      },
      {
        "heroId": 2,
        "matchCount": 95,
        "winCount": 45
      },
      {
        "heroId": 3,
        "matchCount": 112,
        "winCount": 53
      },
      {
        "heroId": 4,
        "matchCount": 6,
        "winCount": 0
      },
      {
        "heroId": 5,
        "matchCount": 230,
        "winCount": 110
      },
      {
        "heroId": 6,
        "matchCount": 2,
        "winCount": 1
      },
      {
        "heroId": 7,
        "matchCount": 510,
        "winCount": 254
      },
      {
        "heroId": 8,
        "matchCount": 6,
        "winCount": 2
      },
      {
        "heroId": 9,
        "matchCount": 530,
        "winCount": 275
      },
      {
        "heroId": 10,
        "matchCount": 8,
        "winCount": 0
      },
      {
        "heroId": 11,
        "matchCount": 30,
        "winCount": 10
      },
      {
        "heroId": 12,
        "matchCount": 1,
        "winCount": 0
      },
      {
        "heroId": 13,
        "matchCount": 10,
        "winCount": 3
      },
      {
        "heroId": 14,
        "matchCount": 1581,
        "winCount": 774
      },
      {
        "heroId": 15,
        "matchCount": 35,
        "winCount": 18
      },
      {
        "heroId": 16,
        "matchCount": 19,
        "winCount": 7
      },
      {
        "heroId": 17,
        "matchCount": 14,
        "winCount": 9
      },
      {
        "heroId": 18,
        "matchCount": 12,
        "winCount": 10
      },
      {
        "heroId": 19,
        "matchCount": 923,
        "winCount": 483
      },
      {
        "heroId": 20,
        "matchCount": 230,
        "winCount": 112
      },
      {
        "heroId": 21,
        "matchCount": 962,
        "winCount": 468
      },
      {
        "heroId": 22,
        "matchCount": 751,
        "winCount": 361
      },
      {
        "heroId": 23,
        "matchCount": 19,
        "winCount": 9
      },
      {
        "heroId": 25,
        "matchCount": 129,
        "winCount": 62
      },
      {
        "heroId": 26,
        "matchCount": 1147,
        "winCount": 577
      },
      {
        "heroId": 27,
        "matchCount": 685,
        "winCount": 361
      },
      {
        "heroId": 28,
        "matchCount": 14,
        "winCount": 6
      },
      {
        "heroId": 29,
        "matchCount": 20,
        "winCount": 13
      },
      {
        "heroId": 30,
        "matchCount": 526,
        "winCount": 255
      },
      {
        "heroId": 31,
        "matchCount": 444,
        "winCount": 237
      },
      {
        "heroId": 32,
        "matchCount": 71,
        "winCount": 32
      },
      {
        "heroId": 33,
        "matchCount": 67,
        "winCount": 30
      },
      {
        "heroId": 34,
        "matchCount": 70,
        "winCount": 31
      },
      {
        "heroId": 35,
        "matchCount": 393,
        "winCount": 179
      },
      {
        "heroId": 36,
        "matchCount": 15,
        "winCount": 6
      },
      {
        "heroId": 37,
        "matchCount": 195,
        "winCount": 91
      },
      {
        "heroId": 38,
        "matchCount": 14,
        "winCount": 10
      },
      {
        "heroId": 39,
        "matchCount": 238,
        "winCount": 108
      },
      {
        "heroId": 40,
        "matchCount": 651,
        "winCount": 343
      },
      {
        "heroId": 41,
        "matchCount": 151,
        "winCount": 77
      },
      {
        "heroId": 42,
        "matchCount": 11,
        "winCount": 5
      },
      {
        "heroId": 43,
        "matchCount": 23,
        "winCount": 14
      },
      {
        "heroId": 44,
        "matchCount": 8,
        "winCount": 4
      },
      {
        "heroId": 45,
        "matchCount": 207,
        "winCount": 121
      },
      {
        "heroId": 47,
        "matchCount": 48,
        "winCount": 19
      },
      {
        "heroId": 48,
        "matchCount": 13,
        "winCount": 5
      },
      {
        "heroId": 49,
        "matchCount": 4,
        "winCount": 2
      },
      {
        "heroId": 50,
        "matchCount": 148,
        "winCount": 79
      },
      {
        "heroId": 51,
        "matchCount": 392,
        "winCount": 203
      },
      {
        "heroId": 52,
        "matchCount": 61,
        "winCount": 25
      },
      {
        "heroId": 53,
        "matchCount": 385,
        "winCount": 167
      },
      {
        "heroId": 54,
        "matchCount": 8,
        "winCount": 5
      },
      {
        "heroId": 55,
        "matchCount": 8,
        "winCount": 6
      },
      {
        "heroId": 56,
        "matchCount": 44,
        "winCount": 17
      },
      {
        "heroId": 57,
        "matchCount": 105,
        "winCount": 62
      },
      {
        "heroId": 58,
        "matchCount": 76,
        "winCount": 30
      },
      {
        "heroId": 59,
        "matchCount": 57,
        "winCount": 19
      },
      {
        "heroId": 60,
        "matchCount": 21,
        "winCount": 12
      },
      {
        "heroId": 61,
        "matchCount": 2,
        "winCount": 0
      },
      {
        "heroId": 62,
        "matchCount": 837,
        "winCount": 447
      },
      {
        "heroId": 63,
        "matchCount": 743,
        "winCount": 374
      },
      {
        "heroId": 64,
        "matchCount": 672,
        "winCount": 338
      },
      {
        "heroId": 65,
        "matchCount": 106,
        "winCount": 47
      },
      {
        "heroId": 66,
        "matchCount": 36,
        "winCount": 19
      },
      {
        "heroId": 67,
        "matchCount": 2,
        "winCount": 1
      },
      {
        "heroId": 68,
        "matchCount": 299,
        "winCount": 160
      },
      {
        "heroId": 69,
        "matchCount": 29,
        "winCount": 17
      },
      {
        "heroId": 70,
        "matchCount": 8,
        "winCount": 5
      },
      {
        "heroId": 71,
        "matchCount": 1354,
        "winCount": 697
      },
      {
        "heroId": 72,
        "matchCount": 96,
        "winCount": 45
      },
      {
        "heroId": 73,
        "matchCount": 201,
        "winCount": 119
      },
      {
        "heroId": 74,
        "matchCount": 592,
        "winCount": 308
      },
      {
        "heroId": 75,
        "matchCount": 364,
        "winCount": 163
      },
      {
        "heroId": 76,
        "matchCount": 8,
        "winCount": 2
      },
      {
        "heroId": 77,
        "matchCount": 10,
        "winCount": 5
      },
      {
        "heroId": 78,
        "matchCount": 20,
        "winCount": 9
      },
      {
        "heroId": 79,
        "matchCount": 357,
        "winCount": 163
      },
      {
        "heroId": 80,
        "matchCount": 8,
        "winCount": 3
      },
      {
        "heroId": 81,
        "matchCount": 17,
        "winCount": 10
      },
      {
        "heroId": 82,
        "matchCount": 1,
        "winCount": 0
      },
      {
        "heroId": 83,
        "matchCount": 233,
        "winCount": 124
      },
      {
        "heroId": 84,
        "matchCount": 456,
        "winCount": 226
      },
      {
        "heroId": 85,
        "matchCount": 285,
        "winCount": 140
      },
      {
        "heroId": 86,
        "matchCount": 1801,
        "winCount": 920
      },
      {
        "heroId": 87,
        "matchCount": 327,
        "winCount": 152
      },
      {
        "heroId": 88,
        "matchCount": 653,
        "winCount": 357
      },
      {
        "heroId": 89,
        "matchCount": 12,
        "winCount": 6
      },
      {
        "heroId": 90,
        "matchCount": 145,
        "winCount": 78
      },
      {
        "heroId": 91,
        "matchCount": 74,
        "winCount": 37
      },
      {
        "heroId": 92,
        "matchCount": 89,
        "winCount": 40
      },
      {
        "heroId": 93,
        "matchCount": 80,
        "winCount": 42
      },
      {
        "heroId": 94,
        "matchCount": 4,
        "winCount": 1
      },
      {
        "heroId": 95,
        "matchCount": 6,
        "winCount": 3
      },
      {
        "heroId": 96,
        "matchCount": 16,
        "winCount": 6
      },
      {
        "heroId": 97,
        "matchCount": 378,
        "winCount": 195
      },
      {
        "heroId": 98,
        "matchCount": 14,
        "winCount": 5
      },
      {
        "heroId": 99,
        "matchCount": 6,
        "winCount": 1
      },
      {
        "heroId": 100,
        "matchCount": 773,
        "winCount": 362
      },
      {
        "heroId": 101,
        "matchCount": 1360,
        "winCount": 670
      },
      {
        "heroId": 102,
        "matchCount": 55,
        "winCount": 27
      },
      {
        "heroId": 103,
        "matchCount": 72,
        "winCount": 37
      },
      {
        "heroId": 104,
        "matchCount": 11,
        "winCount": 4
      },
      {
        "heroId": 105,
        "matchCount": 719,
        "winCount": 336
      },
      {
        "heroId": 106,
        "matchCount": 56,
        "winCount": 29
      },
      {
        "heroId": 107,
        "matchCount": 393,
        "winCount": 209
      },
      {
        "heroId": 108,
        "matchCount": 18,
        "winCount": 9
      },
      {
        "heroId": 109,
        "matchCount": 24,
        "winCount": 8
      },
      {
        "heroId": 110,
        "matchCount": 393,
        "winCount": 197
      },
      {
        "heroId": 111,
        "matchCount": 113,
        "winCount": 58
      },
      {
        "heroId": 112,
        "matchCount": 256,
        "winCount": 135
      },
      {
        "heroId": 113,
        "matchCount": 10,
        "winCount": 5
      },
      {
        "heroId": 114,
        "matchCount": 60,
        "winCount": 23
      },
      {
        "heroId": 119,
        "matchCount": 606,
        "winCount": 304
      },
      {
        "heroId": 120,
        "matchCount": 1,
        "winCount": 0
      },
      {
        "heroId": 121,
        "matchCount": 278,
        "winCount": 142
      },
      {
        "heroId": 123,
        "matchCount": 789,
        "winCount": 412
      },
      {
        "heroId": 126,
        "matchCount": 87,
        "winCount": 49
      },
      {
        "heroId": 128,
        "matchCount": 771,
        "winCount": 395
      },
      {
        "heroId": 129,
        "matchCount": 35,
        "winCount": 19
      },
      {
        "heroId": 131,
        "matchCount": 340,
        "winCount": 165
      },
      {
        "heroId": 135,
        "matchCount": 76,
        "winCount": 40
      },
      {
        "heroId": 136,
        "matchCount": 158,
        "winCount": 69
      },
      {
        "heroId": 137,
        "matchCount": 18,
        "winCount": 9
      },
      {
        "heroId": 138,
        "matchCount": 200,
        "winCount": 89
      },
      {
        "heroId": 145,
        "matchCount": 6,
        "winCount": 5
      },
      {
        "heroId": 155,
        "matchCount": 401,
        "winCount": 201
      }
    ],
    "winWeek": null
  },
  "heroesPos5": {
    "winDay": [
      {
        "heroId": 1,
        "matchCount": 7,
        "winCount": 2
      },
      {
        "heroId": 2,
        "matchCount": 58,
        "winCount": 24
      },
      {
        "heroId": 3,
        "matchCount": 232,
        "winCount": 125
      },
      {
        "heroId": 4,
        "matchCount": 1,
        "winCount": 0
      },
      {
        "heroId": 5,
        "matchCount": 971,
        "winCount": 505
      },
      {
        "heroId": 6,
        "matchCount": 8,
        "winCount": 4
      },
      {
        "heroId": 7,
        "matchCount": 101,
        "winCount": 45
      },
      {
        "heroId": 8,
        "matchCount": 5,
        "winCount": 3
      },
      {
        "heroId": 9,
        "matchCount": 229,
        "winCount": 128
      },
      {
        "heroId": 10,
        "matchCount": 13,
        "winCount": 5
      },
      {
        "heroId": 11,
        "matchCount": 28,
        "winCount": 11
      },
      {
        "heroId": 13,
        "matchCount": 3,
        "winCount": 1
      },
      {
        "heroId": 14,
        "matchCount": 1181,
        "winCount": 576
      },
      {
        "heroId": 15,
        "matchCount": 27,
        "winCount": 9
      },
      {
        "heroId": 16,
        "matchCount": 5,
        "winCount": 1
      },
      {
        "heroId": 17,
        "matchCount": 6,
        "winCount": 1
      },
      {
        "heroId": 18,
        "matchCount": 31,
        "winCount": 16
      },
      {
        "heroId": 19,
        "matchCount": 175,
        "winCount": 79
      },
      {
        "heroId": 20,
        "matchCount": 268,
        "winCount": 149
      },
      {
        "heroId": 21,
        "matchCount": 269,
        "winCount": 114
      },
      {
        "heroId": 22,
        "matchCount": 372,
        "winCount": 182
      },
      {
        "heroId": 23,
        "matchCount": 12,
        "winCount": 4
      },
      {
        "heroId": 25,
        "matchCount": 59,
        "winCount": 34
      },
      {
        "heroId": 26,
        "matchCount": 1700,
        "winCount": 817
      },
      {
        "heroId": 27,
        "matchCount": 1183,
        "winCount": 592
      },
      {
        "heroId": 28,
        "matchCount": 8,
        "winCount": 2
      },
      {
        "heroId": 29,
        "matchCount": 12,
        "winCount": 5
      },
      {
        "heroId": 30,
        "matchCount": 1150,
        "winCount": 587
      },
      {
        "heroId": 31,
        "matchCount": 1360,
        "winCount": 727
      },
      {
        "heroId": 32,
        "matchCount": 17,
        "winCount": 10
      },
      {
        "heroId": 33,
        "matchCount": 39,
        "winCount": 18
      },
      {
        "heroId": 34,
        "matchCount": 70,
        "winCount": 34
      },
      {
        "heroId": 35,
        "matchCount": 135,
        "winCount": 55
      },
      {
        "heroId": 36,
        "matchCount": 4,
        "winCount": 1
      },
      {
        "heroId": 37,
        "matchCount": 1411,
        "winCount": 649
      },
      {
        "heroId": 38,
        "matchCount": 8,
        "winCount": 1
      },
      {
        "heroId": 39,
        "matchCount": 79,
        "winCount": 37
      },
      {
        "heroId": 40,
        "matchCount": 608,
        "winCount": 314
      },
      {
        "heroId": 41,
        "matchCount": 40,
        "winCount": 21
      },
      {
        "heroId": 42,
        "matchCount": 1,
        "winCount": 1
      },
      {
        "heroId": 43,
        "matchCount": 28,
        "winCount": 16
      },
      {
        "heroId": 44,
        "matchCount": 8,
        "winCount": 1
      },
      {
        "heroId": 45,
        "matchCount": 236,
        "winCount": 119
      },
      {
        "heroId": 46,
        "matchCount": 5,
        "winCount": 1
      },
      {
        "heroId": 47,
        "matchCount": 50,
        "winCount": 28
      },
      {
        "heroId": 48,
        "matchCount": 12,
        "winCount": 5
      },
      {
        "heroId": 49,
        "matchCount": 5,
        "winCount": 3
      },
      {
        "heroId": 50,
        "matchCount": 552,
        "winCount": 312
      },
      {
        "heroId": 51,
        "matchCount": 531,
        "winCount": 274
      },
      {
        "heroId": 52,
        "matchCount": 30,
        "winCount": 12
      },
      {
        "heroId": 53,
        "matchCount": 137,
        "winCount": 61
      },
      {
        "heroId": 54,
        "matchCount": 10,
        "winCount": 3
      },
      {
        "heroId": 55,
        "matchCount": 6,
        "winCount": 3
      },
      {
        "heroId": 56,
        "matchCount": 10,
        "winCount": 6
      },
      {
        "heroId": 57,
        "matchCount": 332,
        "winCount": 181
      },
      {
        "heroId": 58,
        "matchCount": 128,
        "winCount": 63
      },
      {
        "heroId": 59,
        "matchCount": 60,
        "winCount": 22
      },
      {
        "heroId": 60,
        "matchCount": 11,
        "winCount": 5
      },
      {
        "heroId": 61,
        "matchCount": 2,
        "winCount": 1
      },
      {
        "heroId": 62,
        "matchCount": 158,
        "winCount": 81
      },
      {
        "heroId": 63,
        "matchCount": 309,
        "winCount": 161
      },
      {
        "heroId": 64,
        "matchCount": 1975,
        "winCount": 926
      },
      {
        "heroId": 65,
        "matchCount": 73,
        "winCount": 36
      },
      {
        "heroId": 66,
        "matchCount": 188,
        "winCount": 89
      },
      {
        "heroId": 67,
        "matchCount": 4,
        "winCount": 3
      },
      {
        "heroId": 68,
        "matchCount": 702,
        "winCount": 373
      },
      {
        "heroId": 69,
        "matchCount": 23,
        "winCount": 11
      },
      {
        "heroId": 70,
        "matchCount": 6,
        "winCount": 3
      },
      {
        "heroId": 71,
        "matchCount": 230,
        "winCount": 107
      },
      {
        "heroId": 72,
        "matchCount": 80,
        "winCount": 40
      },
      {
        "heroId": 73,
        "matchCount": 164,
        "winCount": 77
      },
      {
        "heroId": 74,
        "matchCount": 193,
        "winCount": 91
      },
      {
        "heroId": 75,
        "matchCount": 669,
        "winCount": 315
      },
      {
        "heroId": 76,
        "matchCount": 3,
        "winCount": 1
      },
      {
        "heroId": 77,
        "matchCount": 10,
        "winCount": 6
      },
      {
        "heroId": 78,
        "matchCount": 29,
        "winCount": 13
      },
      {
        "heroId": 79,
        "matchCount": 516,
        "winCount": 265
      },
      {
        "heroId": 80,
        "matchCount": 17,
        "winCount": 7
      },
      {
        "heroId": 81,
        "matchCount": 17,
        "winCount": 10
      },
      {
        "heroId": 82,
        "matchCount": 2,
        "winCount": 1
      },
      {
        "heroId": 83,
        "matchCount": 1025,
        "winCount": 580
      },
      {
        "heroId": 84,
        "matchCount": 882,
        "winCount": 448
      },
      {
        "heroId": 85,
        "matchCount": 578,
        "winCount": 322
      },
      {
        "heroId": 86,
        "matchCount": 682,
        "winCount": 343
      },
      {
        "heroId": 87,
        "matchCount": 1185,
        "winCount": 602
      },
      {
        "heroId": 88,
        "matchCount": 150,
        "winCount": 83
      },
      {
        "heroId": 89,
        "matchCount": 23,
        "winCount": 10
      },
      {
        "heroId": 90,
        "matchCount": 64,
        "winCount": 34
      },
      {
        "heroId": 91,
        "matchCount": 290,
        "winCount": 145
      },
      {
        "heroId": 92,
        "matchCount": 39,
        "winCount": 24
      },
      {
        "heroId": 93,
        "matchCount": 57,
        "winCount": 25
      },
      {
        "heroId": 94,
        "matchCount": 2,
        "winCount": 0
      },
      {
        "heroId": 95,
        "matchCount": 6,
        "winCount": 2
      },
      {
        "heroId": 96,
        "matchCount": 10,
        "winCount": 6
      },
      {
        "heroId": 97,
        "matchCount": 212,
        "winCount": 111
      },
      {
        "heroId": 98,
        "matchCount": 10,
        "winCount": 6
      },
      {
        "heroId": 99,
        "matchCount": 8,
        "winCount": 2
      },
      {
        "heroId": 100,
        "matchCount": 789,
        "winCount": 362
      },
      {
        "heroId": 101,
        "matchCount": 545,
        "winCount": 259
      },
      {
        "heroId": 102,
        "matchCount": 213,
        "winCount": 103
      },
      {
        "heroId": 103,
        "matchCount": 103,
        "winCount": 65
      },
      {
        "heroId": 104,
        "matchCount": 17,
        "winCount": 8
      },
      {
        "heroId": 105,
        "matchCount": 394,
        "winCount": 193
      },
      {
        "heroId": 106,
        "matchCount": 10,
        "winCount": 4
      },
      {
        "heroId": 107,
        "matchCount": 87,
        "winCount": 29
      },
      {
        "heroId": 108,
        "matchCount": 10,
        "winCount": 4
      },
      {
        "heroId": 109,
        "matchCount": 18,
        "winCount": 12
      },
      {
        "heroId": 110,
        "matchCount": 242,
        "winCount": 128
      },
      {
        "heroId": 111,
        "matchCount": 404,
        "winCount": 204
      },
      {
        "heroId": 112,
        "matchCount": 461,
        "winCount": 251
      },
      {
        "heroId": 113,
        "matchCount": 16,
        "winCount": 10
      },
      {
        "heroId": 114,
        "matchCount": 30,
        "winCount": 9
      },
      {
        "heroId": 119,
        "matchCount": 385,
        "winCount": 215
      },
      {
        "heroId": 120,
        "matchCount": 4,
        "winCount": 0
      },
      {
        "heroId": 121,
        "matchCount": 296,
        "winCount": 143
      },
      {
        "heroId": 123,
        "matchCount": 317,
        "winCount": 156
      },
      {
        "heroId": 126,
        "matchCount": 29,
        "winCount": 15
      },
      {
        "heroId": 128,
        "matchCount": 499,
        "winCount": 223
      },
      {
        "heroId": 129,
        "matchCount": 25,
        "winCount": 10
      },
      {
        "heroId": 131,
        "matchCount": 489,
        "winCount": 250
      },
      {
        "heroId": 135,
        "matchCount": 43,
        "winCount": 20
      },
      {
        "heroId": 136,
        "matchCount": 232,
        "winCount": 101
      },
      {
        "heroId": 137,
        "matchCount": 11,
        "winCount": 4
      },
      {
        "heroId": 138,
        "matchCount": 73,
        "winCount": 31
      },
      {
        "heroId": 145,
        "matchCount": 1,
        "winCount": 0
      },
      {
        "heroId": 155,
        "matchCount": 503,
        "winCount": 263
      }
    ],
    "winWeek": null
  }
}
